{
    "validation_key": "lat_ti-u-hxys-u",
    "ui_label": "Latitude",
    "description": "Latitude is positive northward; its units of degree_north (or equivalent) indicate this explicitly. In a latitude-longitude system defined with respect to a rotated North Pole, the standard name of grid_latitude should be used instead of latitude. Grid latitude is positive in the grid-northward direction, but its units should be plain degree.",
    "area_label": "u",
    "cell_measures": "",
    "cell_methods": "apt-fx",
    "dimensions": [
        "site"
    ],
    "frequency": "fx",
    "horizontal_label": "hxys",
    "model_realm": "atmos",
    "out_name": "lat",
    "physical_parameter_name": "lat",
    "positive": "",
    "remove_cmip6_table": "fx",
    "spatial_shape": "S-na",
    "standard_name": "latitude",
    "temporal_label": "ti",
    "temporal_shape": "None",
    "units": "degrees_north",
    "variable_root": "lat",
    "vertical_label": "u",
    "@context": "_context",
    "@type": [
        "wcrp:variable",
        "esgvoc:Variable",
        "vr"
    ],
    "@id": "lat-ti-u-hxys-u"
}
