{
    "validation_key": "rlu_tavg-alh-hxy-u",
    "ui_label": "Upwelling Longwave Radiation",
    "description": "Includes also the fluxes at the surface and TOA.",
    "area_label": "u",
    "cell_measures": "area: areacella",
    "cell_methods": "amn-twm",
    "dimensions": [
        "longitude",
        "latitude",
        "alevhalf",
        "time"
    ],
    "frequency": "mon",
    "horizontal_label": "hxy",
    "model_realm": "atmos",
    "out_name": "rlu",
    "physical_parameter_name": "rlu",
    "positive": "up",
    "remove_cmip6_table": "CFmon",
    "spatial_shape": "XY-AH",
    "standard_name": "upwelling_longwave_flux_in_air",
    "temporal_label": "tavg",
    "temporal_shape": "time-intv",
    "units": "W m-2",
    "variable_root": "rlu",
    "vertical_label": "alh",
    "@context": "_context",
    "@type": [
        "wcrp:variable",
        "esgvoc:Variable",
        "vr"
    ],
    "@id": "rlu-tavg-alh-hxy-u"
}
