{
    "validation_key": "tntc_tpt-al-hxys-u",
    "ui_label": "Tendency of Air Temperature Due to Convection",
    "description": "Tendencies from cumulus convection scheme.",
    "area_label": "u",
    "cell_measures": "",
    "cell_methods": "apt-tpt",
    "dimensions": [
        "alevel",
        "site",
        "time1"
    ],
    "frequency": "subhr",
    "horizontal_label": "hxys",
    "model_realm": "atmos",
    "out_name": "tntc",
    "physical_parameter_name": "tntc",
    "positive": "",
    "remove_cmip6_table": "CFsubhr",
    "spatial_shape": "S-A",
    "standard_name": "tendency_of_air_temperature_due_to_convection",
    "temporal_label": "tpt",
    "temporal_shape": "time-point",
    "units": "K s-1",
    "variable_root": "tntc",
    "vertical_label": "al",
    "@context": "_context",
    "@type": [
        "wcrp:variable",
        "esgvoc:Variable",
        "vr"
    ],
    "@id": "tntc-tpt-al-hxys-u"
}
