{
    "validation_key": "vsfcorr_tavg-u-hxy-sea",
    "ui_label": "Virtual Salt Flux Correction",
    "description": "It is set to zero in models which receive a real water flux.",
    "area_label": "sea",
    "cell_measures": "area: areacello",
    "cell_methods": "amns-tmn",
    "dimensions": [
        "longitude",
        "latitude",
        "time"
    ],
    "frequency": "mon",
    "horizontal_label": "hxy",
    "model_realm": "ocean",
    "out_name": "vsfcorr",
    "physical_parameter_name": "vsfcorr",
    "positive": "",
    "remove_cmip6_table": "Omon",
    "spatial_shape": "XY-na",
    "standard_name": "virtual_salt_flux_correction",
    "temporal_label": "tavg",
    "temporal_shape": "time-intv",
    "units": "kg m-2 s-1",
    "variable_root": "vsfcorr",
    "vertical_label": "u",
    "@context": "_context",
    "@type": [
        "wcrp:variable",
        "esgvoc:Variable",
        "vr"
    ],
    "@id": "vsfcorr-tavg-u-hxy-sea"
}
