{
    "validation_key": "wetlandFrac_tavg-u-hxy-u",
    "ui_label": "Wetland Percentage Cover",
    "description": "Percentage of grid cell covered by wetland. Report only one year if  fixed percentage is used, or time series if values are determined dynamically.",
    "area_label": "u",
    "cell_measures": "area: areacella",
    "cell_methods": "amn-twm",
    "dimensions": [
        "longitude",
        "latitude",
        "time",
        "typewetla"
    ],
    "frequency": "mon",
    "horizontal_label": "hxy",
    "model_realm": "land",
    "out_name": "wetlandFrac",
    "physical_parameter_name": "wetlandFrac",
    "positive": "",
    "remove_cmip6_table": "Emon",
    "spatial_shape": "XY-na",
    "standard_name": "area_fraction",
    "temporal_label": "tavg",
    "temporal_shape": "time-intv",
    "units": "%",
    "variable_root": "wetlandFrac",
    "vertical_label": "u",
    "@context": "_context",
    "@type": [
        "wcrp:variable",
        "esgvoc:Variable",
        "vr"
    ],
    "@id": "wetlandfrac-tavg-u-hxy-u"
}
