{
    "id": "chegpso4_tavg-al-hxy-u",
    "validation-key": "chegpso4_tavg-al-hxy-u",
    "ui-label": "Gas-Phase Production Rate of SO4",
    "description": "proposed name: tendency\\_of\\_atmosphere\\_mass\\_content\\_of\\_sulfate\\_dry\\_aerosol\\_due\\_to\\_gas\\_phase\\_net\\_chemical\\_production",
    "area-label": "u",
    "cell-measures": "area: areacella",
    "cell-methods": "area: time: mean",
    "dimensions": [
        "longitude",
        "latitude",
        "alevel",
        "time"
    ],
    "horizontal-label": "hxy",
    "model-realm": "aerosol",
    "physical-parameter-name": "chegpso4",
    "standard-name": "tendency_of_atmosphere_mass_content_of_sulfate_dry_aerosol_particles_due_to_gaseous_phase_net_chemical_production",
    "temporal-label": "tavg",
    "units": "kg m-2 s-1",
    "variable-root": "chegpso4",
    "vertical-label": "al",
    "@context": "_context_",
    "type": [
        "wcrp:variable",
        "variable-registry"
    ]
}