{
    "id": "friver_tavg-u-hxy-sea",
    "validation-key": "friver_tavg-u-hxy-sea",
    "ui-label": "Water Flux into Sea Water from Rivers",
    "description": "computed as the river flux of water into the ocean divided by the area of the ocean portion of the grid cell.",
    "variable-root": "friver",
    "temporal-label": "tavg",
    "vertical-label": "u",
    "horizontal-label": "hxy",
    "area-label": "sea",
    "remove-cmip6-table": "Omon",
    "frequency": "mon",
    "standard-name": "water_flux_into_sea_water_from_rivers",
    "units": "kg m-2 s-1",
    "cell-methods": "amns-tmn",
    "cell-measures": "area: areacello",
    "dimensions": [
        "longitude",
        "latitude",
        "time"
    ],
    "out-name": "friver",
    "type": [
        "wcrp:variable",
        "variable-registry"
    ],
    "positive": "",
    "spatial-shape": "XY-na",
    "temporal-shape": "time-intv",
    "physical-parameter-name": "friver",
    "model-realm": "ocean",
    "@context": "_context_"
}