{
    "@context": "_context_",
    "id": "ho2-tavg-p39-hy-air",
    "type": [
        "wcrp:variable",
        "variable-registry"
    ],
    "area-label": "air",
    "cell-measures": "",
    "cell-methods": "zmeana-twm",
    "description": "Mole fraction is used in the construction mole_fraction_of_X_in_Y, where X is a material constituent of Y.  The chemical formula of hydroperoxyl radical is HO2.",
    "dimensions": [
        "latitude",
        "plev39",
        "time"
    ],
    "frequency": "mon",
    "horizontal-label": "hy",
    "model-realm": "aerosol",
    "out-name": "ho2",
    "physical-parameter-name": "ho2",
    "positive": "",
    "remove-cmip6-table": "AERmonZ",
    "spatial-shape": "Y-P39",
    "standard-name": "mole_fraction_of_hydroperoxyl_radical_in_air",
    "temporal-label": "tavg",
    "temporal-shape": "time-intv",
    "ui-label": "HO2 Volume Mixing Ratio",
    "units": "mol mol-1",
    "validation-key": "ho2_tavg-p39-hy-air",
    "variable-root": "ho2",
    "vertical-label": "p39"
}
