{
    "@context": "_context_",
    "id": "loadss-tavg-u-hxy-u",
    "type": [
        "wcrp:variable",
        "variable-registry"
    ],
    "area-label": "u",
    "cell-measures": "area: areacella",
    "cell-methods": "amn-twm",
    "description": "The total dry mass of sea salt aerosol particles per unit area.",
    "dimensions": [
        "longitude",
        "latitude",
        "time"
    ],
    "frequency": "day",
    "horizontal-label": "hxy",
    "model-realm": "atmos",
    "out-name": "loadss",
    "physical-parameter-name": "loadss",
    "positive": "",
    "remove-cmip6-table": "Eday",
    "spatial-shape": "XY-na",
    "standard-name": "atmosphere_mass_content_of_sea_salt_dry_aerosol_particles",
    "temporal-label": "tavg",
    "temporal-shape": "time-intv",
    "ui-label": "Load of Sea-Salt Aerosol",
    "units": "kg m-2",
    "validation-key": "loadss_tavg-u-hxy-u",
    "variable-root": "loadss",
    "vertical-label": "u"
}
