{
    "id": "pbo_tavg-u-hxy-sea",
    "validation-key": "pbo_tavg-u-hxy-sea",
    "ui-label": "Sea Water Pressure at Sea Floor",
    "description": "\"Sea water pressure\" is the pressure that exists in the medium of sea water.  It includes the pressure due to overlying sea water, sea ice, air and any other medium that may be present.",
    "area-label": "sea",
    "cell-measures": "area: areacello",
    "cell-methods": "area: mean where sea time: mean",
    "dimensions": [
        "longitude",
        "latitude",
        "time",
        "seafloor"
    ],
    "horizontal-label": "hxy",
    "model-realm": "ocean",
    "physical-parameter-name": "pbo",
    "standard-name": "sea_water_pressure_at_sea_floor",
    "temporal-label": "tavg",
    "units": "Pa",
    "variable-root": "pbo",
    "vertical-label": "u",
    "@context": "_context_",
    "type": [
        "wcrp:variable",
        "variable-registry"
    ]
}