{
    "id": "prsn_tavg-u-hxy-si",
    "validation-key": "prsn_tavg-u-hxy-si",
    "ui-label": "Snow Mass Change Through Snowfall",
    "description": "Rate of change of snow mass due to solid precipitation (i.e. snowfall) falling onto sea ice divided by grid-cell area. Always positive or zero.",
    "variable-root": "prsn",
    "temporal-label": "tavg",
    "vertical-label": "u",
    "horizontal-label": "hxy",
    "area-label": "si",
    "remove-cmip6-table": "SImon",
    "frequency": "mon",
    "standard-name": "snowfall_flux",
    "units": "kg m-2 s-1",
    "cell-methods": "Error: area: time: mean where sea_ice (mask=siconc) not found in cell methods, please register",
    "cell-measures": "area: areacello",
    "dimensions": [
        "longitude",
        "latitude",
        "time"
    ],
    "out-name": "sisndmasssnf",
    "type": [
        "wcrp:variable",
        "variable-registry"
    ],
    "positive": "",
    "spatial-shape": "XY-na",
    "temporal-shape": "time-intv",
    "physical-parameter-name": "sisndmasssnf",
    "model-realm": "seaice",
    "@context": "_context_"
}