{
    "@context": "_context_",
    "id": "topg-tavg-u-hxy-gis",
    "type": [
        "wcrp:variable",
        "variable-registry"
    ],
    "area-label": "gis",
    "cell-measures": "area: areacellg",
    "cell-methods": "Error: area: time: mean where grounded_ice_sheet (mask=sfgrlf) not found in cell methods, please register",
    "description": "This is needed in case bed rock elevation changes in time",
    "dimensions": [
        "xgre",
        "ygre",
        "time"
    ],
    "frequency": "yr",
    "horizontal-label": "hxy",
    "model-realm": "landice",
    "out-name": "topg",
    "physical-parameter-name": "topg",
    "positive": "",
    "remove-cmip6-table": "IyrGre",
    "spatial-shape": "XYG-na",
    "standard-name": "bedrock_altitude",
    "temporal-label": "tavg",
    "temporal-shape": "time-intv",
    "ui-label": "Bedrock Altitude",
    "units": "m",
    "validation-key": "topg_tavg-u-hxy-gis",
    "variable-root": "topg",
    "vertical-label": "u"
}
