{
    "id": "ts-tpt-u-hxy-u",
    "validation-key": "ts_tpt-u-hxy-u",
    "ui-label": "Surface Temperature",
    "description": "Surface temperature (skin for open ocean)",
    "area-label": "u",
    "cell-measures": "area: areacella",
    "cell-methods": "amn-tpt",
    "dimensions": [
        "longitude",
        "latitude",
        "time1"
    ],
    "frequency": "3hr",
    "horizontal-label": "hxy",
    "model-realm": "atmos",
    "out-name": "ts",
    "physical-parameter-name": "ts",
    "positive": "",
    "remove-cmip6-table": "CF3hr",
    "spatial-shape": "XY-na",
    "standard-name": "surface_temperature",
    "temporal-label": "tpt",
    "temporal-shape": "time-point",
    "units": "K",
    "variable-root": "ts",
    "vertical-label": "u",
    "@context": "_context_",
    "type": [
        "wcrp:variable",
        "variable-registry"
    ]
}
