{
    "id": "tslsi-tavg-u-hxy-u",
    "validation-key": "tslsi_tavg-u-hxy-u",
    "ui-label": "Surface Temperature Where Land or Sea Ice",
    "description": "Surface temperature of all surfaces except open ocean.",
    "area-label": "u",
    "cell-measures": "area: areacella",
    "cell-methods": "amnlsi-twm",
    "dimensions": [
        "longitude",
        "latitude",
        "time"
    ],
    "frequency": "day",
    "horizontal-label": "hxy",
    "model-realm": "land",
    "out-name": "tslsi",
    "physical-parameter-name": "tslsi",
    "positive": "",
    "remove-cmip6-table": "day",
    "spatial-shape": "XY-na",
    "standard-name": "surface_temperature",
    "temporal-label": "tavg",
    "temporal-shape": "time-intv",
    "units": "K",
    "variable-root": "tslsi",
    "vertical-label": "u",
    "@context": "_context_",
    "type": [
        "wcrp:variable",
        "variable-registry"
    ]
}
